signal_cli_douglasadams_42/Attachments.py
signal_cli_douglasadams_42/Client.py
signal_cli_douglasadams_42/Contacts.py
signal_cli_douglasadams_42/Devices.py
signal_cli_douglasadams_42/General.py
signal_cli_douglasadams_42/Groups.py
signal_cli_douglasadams_42/Identities.py
signal_cli_douglasadams_42/Messages.py
signal_cli_douglasadams_42/Profiles.py
signal_cli_douglasadams_42/Reactions.py
signal_cli_douglasadams_42/Search.py
signal_cli_douglasadams_42/__init__.py
signal_cli_douglasadams_42-0.2.0.dist-info/METADATA
signal_cli_douglasadams_42-0.2.0.dist-info/WHEEL
signal_cli_douglasadams_42-0.2.0.dist-info/licenses/LICENSE
signal_cli_douglasadams_42-0.2.0.dist-info/RECORD
