Metadata-Version: 2.1
Name: signal_cli_douglasadams_42
Version: 0.2.0
Summary: A python wrapper for the signal-cli-rest-api created by bbernhard on github
Project-URL: signal-cli-rest-api, https://github.com/bbernhard/signal-cli-rest-api
Project-URL: signal-cli-rest-api swagger, https://bbernhard.github.io/signal-cli-rest-api/
Project-URL: documentation, https://fhune.de/signal_cli_documentation/
License-File: LICENSE
Classifier: License :: OSI Approved :: GNU Lesser General Public License v3 (LGPLv3)
Classifier: Operating System :: OS Independent
Classifier: Programming Language :: Python :: 3
Requires-Python: >=3.9
Requires-Dist: filetype==1.2.0
Requires-Dist: pathlib==1.0.1
Requires-Dist: requests==2.22.0
Requires-Dist: typing==3.7.4.3
